EcoNameTranslator/__init__.py
EcoNameTranslator/children.py
EcoNameTranslator/classify.py
EcoNameTranslator/downstream.py
EcoNameTranslator/lowest_rank_intersection.py
EcoNameTranslator/speciesValidation.py
EcoNameTranslator/synonyms.py
EcoNameTranslator/to_common.py
EcoNameTranslator/to_scientific.py
EcoNameTranslator/to_species.py
EcoNameTranslator/upstream.py
EcoNameTranslator/externalAPIs/__init__.py
EcoNameTranslator/externalAPIs/apiUtils.py
EcoNameTranslator/externalAPIs/gbif.py
EcoNameTranslator/externalAPIs/gnr.py
EcoNameTranslator/externalAPIs/itis.py
EcoNameTranslator/externalAPIs/gbifTools/__init__.py
EcoNameTranslator/externalAPIs/gbifTools/diveDownTaxaTree.py
EcoNameTranslator/externalAPIs/gbifTools/taxaProfiling.py
EcoNameTranslator/externalAPIs/gbifTools/taxaToSpecies.py
EcoNameTranslator/externalAPIs/gnrTools/__init__.py
EcoNameTranslator/externalAPIs/gnrTools/taxaProfiling.py
EcoNameTranslator/externalAPIs/itisTools/__init__.py
EcoNameTranslator/externalAPIs/itisTools/commonToScientific.py
EcoNameTranslator/externalAPIs/itisTools/downstreamHierarchy.py
EcoNameTranslator/externalAPIs/itisTools/scientificToCommon.py
EcoNameTranslator/externalAPIs/itisTools/synonymMatching.py
EcoNameTranslator/externalAPIs/itisTools/tsnMatching.py
EcoNameTranslator/services/__init__.py
EcoNameTranslator/services/consensus.py
EcoNameTranslator/services/constants.py
EcoNameTranslator/services/dataCleaning.py
EcoNameTranslator/services/findDownstream.py
EcoNameTranslator/services/mapCommonToScientific.py
EcoNameTranslator/services/mapHigherTaxaToSpecies.py
EcoNameTranslator/services/mapScientificToCommon.py
EcoNameTranslator/services/profileTaxonomy.py
EcoNameTranslator/services/services.py
EcoNameTranslator/services/tagWithTaxaLevel.py
EcoNameTranslator/services/taxaSynonyms.py
EcoNameTranslator-2.1.dist-info/METADATA
EcoNameTranslator-2.1.dist-info/WHEEL
EcoNameTranslator-2.1.dist-info/top_level.txt
EcoNameTranslator-2.1.dist-info/RECORD
