Metadata-Version: 2.1
Name: EcoNameTranslator
Version: 2.1
Summary: A lightweight but powerful package for full management and translation of ecological names
Home-page: https://github.com/Daniel-Davies/MedeinaTranslator
Author: Daniel Davies
Author-email: dd16785@bristol.ac.uk
License: UNKNOWN
Platform: UNKNOWN
Classifier: Programming Language :: Python :: 3
Classifier: License :: OSI Approved :: MIT License
Classifier: Operating System :: OS Independent
Requires-Dist: taxon-parser
